nxt_editor/__init__.py
nxt_editor-3.2.0.dist-info/LICENSE
nxt_editor-3.2.0.dist-info/METADATA
nxt_editor-3.2.0.dist-info/WHEEL
nxt_editor-3.2.0.dist-info/top_level.txt
nxt_editor-3.2.0.dist-info/RECORD
