Metadata-Version: 2.1
Name: nxt-editor
Version: 3.2.0
Summary: The nxt editor
Home-page: https://github.com/SunriseProductions/nxt
Author: the nxt contributors
Author-email: author@example.com
License: UNKNOWN
Platform: UNKNOWN
Requires-Python: >=2.7, <3
